happymath/__init__.py
happymath/_version.py
happymath/AutoML/__init__.py
happymath/AutoML/base.py
happymath/AutoML/supervised.py
happymath/AutoML/time_series.py
happymath/AutoML/unsupervised.py
happymath/AutoML/core/__init__.py
happymath/AutoML/core/font.py
happymath/AutoML/core/scores.py
happymath/AutoML/core/utils.py
happymath/Decision/__init__.py
happymath/Decision/algorithm/__init__.py
happymath/Decision/algorithm/ahp.py
happymath/Decision/algorithm/aras.py
happymath/Decision/algorithm/borda.py
happymath/Decision/algorithm/bwm.py
happymath/Decision/algorithm/bwm_s.py
happymath/Decision/algorithm/cilos.py
happymath/Decision/algorithm/cocoso.py
happymath/Decision/algorithm/codas.py
happymath/Decision/algorithm/copeland.py
happymath/Decision/algorithm/copras.py
happymath/Decision/algorithm/cpp_tri.py
happymath/Decision/algorithm/cradis.py
happymath/Decision/algorithm/critic.py
happymath/Decision/algorithm/dematel.py
happymath/Decision/algorithm/e_i.py
happymath/Decision/algorithm/e_i_s.py
happymath/Decision/algorithm/e_i_v.py
happymath/Decision/algorithm/e_ii.py
happymath/Decision/algorithm/e_iii.py
happymath/Decision/algorithm/e_iv.py
happymath/Decision/algorithm/e_tri_b.py
happymath/Decision/algorithm/edas.py
happymath/Decision/algorithm/entropy.py
happymath/Decision/algorithm/fucom.py
happymath/Decision/algorithm/fuzzy_ahp.py
happymath/Decision/algorithm/fuzzy_aras.py
happymath/Decision/algorithm/fuzzy_bwm.py
happymath/Decision/algorithm/fuzzy_copras.py
happymath/Decision/algorithm/fuzzy_critic.py
happymath/Decision/algorithm/fuzzy_dematel.py
happymath/Decision/algorithm/fuzzy_edas.py
happymath/Decision/algorithm/fuzzy_fucom.py
happymath/Decision/algorithm/fuzzy_merec.py
happymath/Decision/algorithm/fuzzy_moora.py
happymath/Decision/algorithm/fuzzy_ocra.py
happymath/Decision/algorithm/fuzzy_topsis.py
happymath/Decision/algorithm/fuzzy_vikor.py
happymath/Decision/algorithm/fuzzy_waspas.py
happymath/Decision/algorithm/gra.py
happymath-0.1.5.dist-info/licenses/LICENSE
happymath-0.1.5.dist-info/METADATA
happymath-0.1.5.dist-info/WHEEL
happymath-0.1.5.dist-info/top_level.txt
happymath-0.1.5.dist-info/RECORD
