Metadata-Version: 2.4
Name: happymath
Version: 0.1.5
Summary: Happymath is a high-level mathematical modeling Python library. Its core philosophy lies in reducing users' learning costs through high-level encapsulation, enabling efficient mathematical modeling. It is particularly suitable for mathematical modeling competitions and applied mathematics fields.
Home-page: https://github.com/HappymathLabs/happymath
Author: HappymathLabs
Author-email: HappymathLabs <tonghui_zou@happymath.com.cn>
Maintainer-email: HappymathLabs <tonghui_zou@happymath.com.cn>
License: MIT
Project-URL: Homepage, https://github.com/HappyMathLabs/happymath
Project-URL: Repository, https://github.com/HappyMathLabs/happymath
Project-URL: Documentation, https://github.com/HappyMathLabs/happymath
Project-URL: Bug Tracker, https://github.com/HappyMathLabs/happymath/issues
Keywords: mathematics,machine-learning,optimization,differential-equations,decision-analysis
Classifier: Development Status :: 3 - Alpha
Classifier: Intended Audience :: Science/Research
Classifier: Intended Audience :: Developers
Classifier: License :: OSI Approved :: MIT License
Classifier: Programming Language :: Python :: 3
Classifier: Programming Language :: Python :: 3.11
Classifier: Topic :: Scientific/Engineering :: Mathematics
Classifier: Topic :: Scientific/Engineering :: Artificial Intelligence
Classifier: Topic :: Software Development :: Libraries :: Python Modules
Requires-Python: >=3.11
License-File: LICENSE
Requires-Dist: numpy
Requires-Dist: scipy==1.10.0
Requires-Dist: sympy
Requires-Dist: pandas<2.2.0
Requires-Dist: scikit-learn
Requires-Dist: catboost
Requires-Dist: xgboost
Requires-Dist: pycaret==3.3.2
Requires-Dist: pyomo
Requires-Dist: pymoo
Requires-Dist: matplotlib<3.8.0
Requires-Dist: seaborn
Requires-Dist: dash
Requires-Dist: dash-bootstrap-components
Requires-Dist: panel
Requires-Dist: jupyter_bokeh
Requires-Dist: statsmodels
Requires-Dist: patsy
Requires-Dist: shap
Requires-Dist: umap-learn
Requires-Dist: timeout-decorator
Requires-Dist: py-pde
Requires-Dist: ipython
Requires-Dist: ipykernel
Requires-Dist: watchfiles
Requires-Dist: pyarrow
Provides-Extra: dev
Requires-Dist: pytest>=6.0; extra == "dev"
Requires-Dist: pytest-cov; extra == "dev"
Requires-Dist: black; extra == "dev"
Requires-Dist: flake8; extra == "dev"
Requires-Dist: mypy; extra == "dev"
Provides-Extra: docs
Requires-Dist: sphinx; extra == "docs"
Requires-Dist: sphinx-rtd-theme; extra == "docs"
Requires-Dist: sphinx-autodoc-typehints; extra == "docs"
Provides-Extra: all
Requires-Dist: lightgbm; extra == "all"
Requires-Dist: cylp; extra == "all"
Requires-Dist: swiglpk; extra == "all"
Requires-Dist: PySCIPOpt; extra == "all"
Dynamic: author
Dynamic: home-page
Dynamic: license-file
Dynamic: requires-python
